LICENSE.md
eflips/model/__init__.py
eflips/model/depot.py
eflips/model/general.py
eflips/model/network.py
eflips/model/schedule.py
eflips_db-1.0.0rc3.dist-info/LICENSE.md
eflips_db-1.0.0rc3.dist-info/METADATA
eflips_db-1.0.0rc3.dist-info/WHEEL
eflips_db-1.0.0rc3.dist-info/RECORD
