Metadata-Version: 2.1
Name: eflips-db
Version: 1.0.0rc3
Summary: A common data model for the eflips family of electric vehicle simulation & optimization tools.
Home-page: https://github.com/mpm-tu-berlin/eflips-db
License: AGPL-3.0-or-later
Author: Ludger Heide
Author-email: ludger.heide@tu-berlin.de
Requires-Python: >=3.9,<4.0
Classifier: License :: OSI Approved :: GNU Affero General Public License v3 or later (AGPLv3+)
Classifier: Programming Language :: Python :: 3
Classifier: Programming Language :: Python :: 3.9
Classifier: Programming Language :: Python :: 3.10
Classifier: Programming Language :: Python :: 3.11
Requires-Dist: alembic (>=1.12.1,<2.0.0)
Requires-Dist: geoalchemy2 (>=0.14.2,<0.15.0)
Requires-Dist: psycopg2-binary (>=2.9.9,<3.0.0)
Requires-Dist: sqlalchemy (>=2.0.23,<3.0.0)
Project-URL: Repository, https://github.com/mpm-tu-berlin/eflips-db
